PyQt6/Qt/lib/libQt6Core.so.6
PyQt6/Qt/lib/libQt6DBus.so.6
PyQt6/Qt/lib/libQt6Designer.so.6
PyQt6/Qt/lib/libQt6Gui.so.6
PyQt6/Qt/lib/libQt6Help.so.6
PyQt6/Qt/lib/libQt6Network.so.6
PyQt6/Qt/lib/libQt6OpenGL.so.6
PyQt6/Qt/lib/libQt6OpenGLWidgets.so.6
PyQt6/Qt/lib/libQt6PrintSupport.so.6
PyQt6/Qt/lib/libQt6Qml.so.6
PyQt6/Qt/lib/libQt6QmlModels.so.6
PyQt6/Qt/lib/libQt6QmlWorkerScript.so.6
PyQt6/Qt/lib/libQt6Quick.so.6
PyQt6/Qt/lib/libQt6Quick3D.so.6
PyQt6/Qt/lib/libQt6Quick3DAssetImport.so.6
PyQt6/Qt/lib/libQt6Quick3DRuntimeRender.so.6
PyQt6/Qt/lib/libQt6Quick3DUtils.so.6
PyQt6/Qt/lib/libQt6QuickControls2.so.6
PyQt6/Qt/lib/libQt6QuickControls2Impl.so.6
PyQt6/Qt/lib/libQt6QuickParticles.so.6
PyQt6/Qt/lib/libQt6QuickShapes.so.6
PyQt6/Qt/lib/libQt6QuickTemplates2.so.6
PyQt6/Qt/lib/libQt6QuickTest.so.6
PyQt6/Qt/lib/libQt6QuickWidgets.so.6
PyQt6/Qt/lib/libQt6ShaderTools.so.6
PyQt6/Qt/lib/libQt6Sql.so.6
PyQt6/Qt/lib/libQt6Svg.so.6
PyQt6/Qt/lib/libQt6SvgWidgets.so.6
PyQt6/Qt/lib/libQt6Test.so.6
PyQt6/Qt/lib/libQt6WaylandClient.so.6
PyQt6/Qt/lib/libQt6Widgets.so.6
PyQt6/Qt/lib/libQt6XcbQpa.so.6
PyQt6/Qt/lib/libQt6Xml.so.6
PyQt6/Qt/lib/libicudata.so.56
PyQt6/Qt/lib/libicui18n.so.56
PyQt6/Qt/lib/libicuuc.so.56
PyQt6/Qt/plugins/assetimporters/libassimp.so
PyQt6/Qt/plugins/assetimporters/libuip.so
PyQt6/Qt/plugins/egldeviceintegrations/libqeglfs-emu-integration.so
PyQt6/Qt/plugins/egldeviceintegrations/libqeglfs-kms-egldevice-integration.so
PyQt6/Qt/plugins/egldeviceintegrations/libqeglfs-x11-integration.so
PyQt6/Qt/plugins/generic/libqevdevkeyboardplugin.so
PyQt6/Qt/plugins/generic/libqevdevmouseplugin.so
PyQt6/Qt/plugins/generic/libqevdevtabletplugin.so
PyQt6/Qt/plugins/generic/libqevdevtouchplugin.so
PyQt6/Qt/plugins/generic/libqtuiotouchplugin.so
PyQt6/Qt/plugins/geometryloaders/libdefaultgeometryloader.so
PyQt6/Qt/plugins/iconengines/libqsvgicon.so
PyQt6/Qt/plugins/imageformats/libqgif.so
PyQt6/Qt/plugins/imageformats/libqicns.so
PyQt6/Qt/plugins/imageformats/libqico.so
PyQt6_Qt-6.0.1.dist-info/LICENSE
PyQt6_Qt-6.0.1.dist-info/METADATA
PyQt6_Qt-6.0.1.dist-info/WHEEL
PyQt6_Qt-6.0.1.dist-info/RECORD
