Metadata-Version: 2.1
Name: PyQt6-Qt
Version: 6.0.1
Summary: The subset of a Qt installation needed by PyQt6.
Home-page: https://www.riverbankcomputing.com/software/pyqt/
Author: Riverbank Computing Limited
Author-email: info@riverbankcomputing.com
License: LGPL v3
Platform: Linux
Platform: macOS
Platform: Windows
